<root issues-status="done" commits-status="done"><participant login="jeffects" cnt="1"><period date="201437"><pullrequests>1</pullrequests></period></participant><participant login="buccolo" cnt="2"><period date="201437"><comments>1</comments><commits>1</commits><additions>1</additions><deletions>0</deletions></period></participant><participant login="sebbean" cnt="1"><period date="201417"><pullrequests>1</pullrequests></period></participant><participant login="reinaldob" cnt="1"><period date="201448"><commits>1</commits><additions>3</additions><deletions>3</deletions></period></participant><participant login="schof" cnt="40"><period date="201414"><commits>7</commits><additions>35</additions><deletions>5</deletions></period><period date="201413"><commits>12</commits><additions>26</additions><deletions>17</deletions><comments>1</comments></period><period date="201430"><commits>1</commits><additions>2</additions><deletions>1</deletions></period><period date="201429"><commits>1</commits><additions>9</additions><deletions>7</deletions></period><period date="201418"><commits>1</commits><additions>1</additions><deletions>1</deletions></period><period date="201417"><commits>3</commits><additions>44</additions><deletions>7</deletions></period><period date="201412"><commits>8</commits><additions>251</additions><deletions>65</deletions></period><period date="201416"><commits>2</commits><additions>3</additions><deletions>1</deletions></period><period date="201415"><commits>4</commits><additions>17</additions><deletions>7</deletions></period></participant><participant login="phstc" cnt="5"><period date="201447"><commits>4</commits><additions>8</additions><deletions>7</deletions></period><period date="201420"><commits>1</commits><additions>14</additions><deletions>0</deletions></period></participant><participant login="BDQ" cnt="7"><period date="201446"><commits>3</commits><additions>7</additions><deletions>8</deletions></period><period date="201445"><commits>1</commits><additions>9</additions><deletions>7</deletions></period><period date="201413"><commits>2</commits><additions>1</additions><deletions>0</deletions></period><period date="201417"><commits>1</commits><additions>19</additions><deletions>2</deletions></period></participant><participant login="ric@burton-3.local//ric@burton-3.local//Richard Lister//Richard Lister" cnt="1"><period date="201445"><commits>1</commits><additions>2</additions><deletions>2</deletions></period></participant><participant login="jsqu99" cnt="2"><period date="201413"><comments>1</comments></period><period date="201414"><comments>1</comments></period></participant><participant login="rlister@gmail.com//rlister@gmail.com//Richard Lister//Richard Lister" cnt="6"><period date="201412"><commits>5</commits><additions>54</additions><deletions>7</deletions></period><period date="201415"><commits>1</commits><additions>2</additions><deletions>4</deletions></period></participant></root>