<root issues-status="done" commits-status="done"><participant login="justinclift" cnt="62"><period date="201516"><commits>2</commits><additions>109</additions><deletions>1</deletions></period><period date="201421"><commits>6</commits><additions>25</additions><deletions>28</deletions></period><period date="201413"><commits>18</commits><additions>440</additions><deletions>145</deletions></period><period date="201420"><commits>1</commits><additions>7</additions><deletions>5</deletions></period><period date="201514"><commits>1</commits><additions>5</additions><deletions>2</deletions></period><period date="201509"><commits>5</commits><additions>17</additions><deletions>13</deletions></period><period date="201419"><commits>6</commits><additions>87</additions><deletions>17</deletions></period><period date="201508"><commits>5</commits><additions>11</additions><deletions>1</deletions></period><period date="201418"><commits>2</commits><additions>23</additions><deletions>4</deletions></period><period date="201415"><commits>2</commits><additions>109</additions><deletions>2</deletions></period><period date="201414"><commits>2</commits><additions>320</additions><deletions>116</deletions></period><period date="201506"><commits>3</commits><additions>33</additions><deletions>12</deletions></period><period date="201439"><commits>1</commits><additions>1</additions><deletions>1</deletions></period><period date="201437"><commits>2</commits><additions>2</additions><deletions>1</deletions></period><period date="201428"><commits>3</commits><additions>113</additions><deletions>2</deletions></period><period date="201424"><commits>3</commits><additions>11</additions><deletions>3</deletions></period></participant></root>