<root status="done" page="0"><issue creator="deadtrickster" id="37" assignee="&lt;github.NamedUser.NamedUser object at 0x12e0a9210&gt;" created_at="18/4/2016"><comment creator="michaelklishin" created_at="18/4/2016"/><comment creator="deadtrickster" created_at="18/4/2016"/><comment creator="deadtrickster" created_at="19/4/2016"/><comment creator="michaelklishin" created_at="19/4/2016"/><comment creator="deadtrickster" created_at="21/4/2016"/></issue><issue creator="dumbbell" id="9" assignee="&lt;github.NamedUser.NamedUser object at 0x130681390&gt;" pullrequest="yes" created_at="12/3/2015"><comment creator="dumbbell" created_at="12/3/2015"/></issue><issue creator="gotthardp" id="36" created_at="30/11/2015"><comment creator="dumbbell" created_at="30/11/2015"/><comment creator="gotthardp" created_at="30/11/2015"/><comment creator="michaelklishin" created_at="30/11/2015"/><comment creator="gotthardp" created_at="30/11/2015"/><comment creator="michaelklishin" created_at="30/11/2015"/><comment creator="michaelklishin" created_at="30/11/2015"/><comment creator="dumbbell" created_at="1/12/2015"/><comment creator="gotthardp" created_at="5/12/2015"/></issue><issue creator="dumbbell" id="8" assignee="&lt;github.NamedUser.NamedUser object at 0x1308bcf90&gt;" created_at="12/3/2015"/><issue creator="dumbbell" id="7" assignee="&lt;github.NamedUser.NamedUser object at 0x1308bca10&gt;" created_at="12/3/2015"/><issue creator="dumbbell" id="6" assignee="&lt;github.NamedUser.NamedUser object at 0x1308bc110&gt;" created_at="12/3/2015"><comment creator="dumbbell" created_at="1/4/2015"/></issue><issue creator="michaelklishin" id="35" assignee="&lt;github.NamedUser.NamedUser object at 0x12e0a9650&gt;" created_at="23/11/2015"><comment creator="michaelklishin" created_at="26/11/2015"/></issue><issue creator="dumbbell" id="5" assignee="&lt;github.NamedUser.NamedUser object at 0x1308bcad0&gt;" created_at="11/3/2015"/><issue creator="dumbbell" id="4" assignee="&lt;github.NamedUser.NamedUser object at 0x12e0e5b10&gt;" pullrequest="yes" created_at="26/2/2015"/><issue creator="michaelklishin" id="34" assignee="&lt;github.NamedUser.NamedUser object at 0x130154390&gt;" created_at="20/11/2015"/><issue creator="dumbbell" id="3" assignee="&lt;github.NamedUser.NamedUser object at 0x12e0e59d0&gt;" created_at="25/2/2015"><comment creator="dumbbell" created_at="26/2/2015"/></issue><issue creator="michaelklishin" id="33" assignee="&lt;github.NamedUser.NamedUser object at 0x130154a10&gt;" created_at="31/10/2015"><comment creator="dumbbell" created_at="26/11/2015"/></issue><issue creator="PiotrSikora" id="2" pullrequest="yes" created_at="21/12/2011"><comment creator="PiotrSikora" created_at="5/1/2012"/></issue><issue creator="gotthardp" id="32" created_at="17/9/2015"/><issue creator="romanek-adam" id="31" assignee="&lt;github.NamedUser.NamedUser object at 0x130154ed0&gt;" created_at="31/8/2015"><comment creator="michaelklishin" created_at="10/11/2015"/></issue><issue creator="PiotrSikora" id="1" pullrequest="yes" created_at="21/12/2011"><comment creator="PiotrSikora" created_at="5/1/2012"/></issue><issue creator="dumbbell" id="30" assignee="&lt;github.NamedUser.NamedUser object at 0x12ac520d0&gt;" pullrequest="yes" created_at="11/8/2015"/><issue creator="essen" id="29" assignee="&lt;github.NamedUser.NamedUser object at 0x12ac52e50&gt;" pullrequest="yes" created_at="10/8/2015"/><issue creator="dumbbell" id="28" assignee="&lt;github.NamedUser.NamedUser object at 0x130882810&gt;" pullrequest="yes" created_at="5/8/2015"/><issue creator="dumbbell" id="27" assignee="&lt;github.NamedUser.NamedUser object at 0x1308828d0&gt;" pullrequest="yes" created_at="4/8/2015"/><issue creator="dumbbell" id="26" assignee="&lt;github.NamedUser.NamedUser object at 0x1308820d0&gt;" pullrequest="yes" created_at="4/8/2015"/><issue creator="dumbbell" id="25" assignee="&lt;github.NamedUser.NamedUser object at 0x130882650&gt;" created_at="3/8/2015"/><issue creator="cap10morgan" id="24" assignee="&lt;github.NamedUser.NamedUser object at 0x1301e4590&gt;" pullrequest="yes" created_at="6/6/2015"><comment creator="dumbbell" created_at="9/6/2015"/><comment creator="cap10morgan" created_at="9/6/2015"/><comment creator="dumbbell" created_at="10/6/2015"/></issue><issue creator="michaelklishin" id="23" assignee="&lt;github.NamedUser.NamedUser object at 0x1301e4ed0&gt;" created_at="1/5/2015"/><issue creator="videlalvaro" id="22" assignee="&lt;github.NamedUser.NamedUser object at 0x13028af50&gt;" pullrequest="yes" created_at="14/4/2015"><comment creator="videlalvaro" created_at="15/4/2015"/><comment creator="michaelklishin" created_at="15/4/2015"/></issue><issue creator="dumbbell" id="21" assignee="&lt;github.NamedUser.NamedUser object at 0x13028aed0&gt;" created_at="1/4/2015"><comment creator="dumbbell" created_at="1/4/2015"/></issue><issue creator="dumbbell" id="20" assignee="&lt;github.NamedUser.NamedUser object at 0x130444a90&gt;" created_at="1/4/2015"/><issue creator="dumbbell" id="19" assignee="&lt;github.NamedUser.NamedUser object at 0x130444bd0&gt;" created_at="31/3/2015"/><issue creator="dumbbell" id="18" assignee="&lt;github.NamedUser.NamedUser object at 0x130444690&gt;" created_at="31/3/2015"/><issue creator="dumbbell" id="17" assignee="&lt;github.NamedUser.NamedUser object at 0x13052e050&gt;" created_at="30/3/2015"><comment creator="dumbbell" created_at="30/3/2015"/></issue><issue creator="dumbbell" id="16" assignee="&lt;github.NamedUser.NamedUser object at 0x13052e650&gt;" created_at="20/3/2015"/><issue creator="dumbbell" id="15" assignee="&lt;github.NamedUser.NamedUser object at 0x1302eb710&gt;" created_at="20/3/2015"/><issue creator="dumbbell" id="14" assignee="&lt;github.NamedUser.NamedUser object at 0x1302eb250&gt;" pullrequest="yes" created_at="13/3/2015"/><issue creator="dumbbell" id="13" assignee="&lt;github.NamedUser.NamedUser object at 0x1302ebf50&gt;" created_at="13/3/2015"/><issue creator="dumbbell" id="12" assignee="&lt;github.NamedUser.NamedUser object at 0x1302eb590&gt;" pullrequest="yes" created_at="12/3/2015"/><issue creator="dumbbell" id="11" assignee="&lt;github.NamedUser.NamedUser object at 0x130681f90&gt;" pullrequest="yes" created_at="12/3/2015"/><issue creator="dumbbell" id="10" assignee="&lt;github.NamedUser.NamedUser object at 0x130681d10&gt;" pullrequest="yes" created_at="12/3/2015"/></root>