<root page="0" status="done"><commit additions="1" created_at="28/9/2015" creator="keyki" deletions="8" id="1bb5aac45c262a3dfd0f4f61bf6f6c16babd9ddc" merge="no"/><commit additions="1" created_at="6/9/2015" creator="keyki" deletions="1" id="70dd43b35d089d2b17030238bdefcf85450610fb" merge="no"/><commit additions="1" created_at="23/7/2015" creator="keyki" deletions="1" id="ed24687ce666631adf566a50b0ff318b1a3ed9b8" merge="no"/><commit additions="6" created_at="16/7/2015" creator="keyki" deletions="13" id="045bf3349b1107e5d76679942054ef5346a74919" merge="no"/><commit additions="1" created_at="29/6/2015" creator="akanto" deletions="1" id="f7c2ad9bdc9a3901e416645cbe31dd29df99783c" merge="no"/><commit additions="29" created_at="29/6/2015" creator="akanto" deletions="8" id="b9abe30232d0e710f8b237d40f113253f7e8f989" merge="no"/><commit additions="1" created_at="5/6/2015" creator="keyki" deletions="1" id="1d755c4a248e575a0dbc3d56ea7411181218b71f" merge="no"/><commit additions="1" created_at="1/6/2015" creator="doktoric" deletions="1" id="32ca49434f5413e3a3dad4cc7699104c529f794b" merge="no"/><commit additions="8" created_at="27/5/2015" creator="doktoric" deletions="1" id="904eec80826d7e88c675df8104b00853f93dd0ad" merge="no"/><commit additions="28" created_at="13/5/2015" creator="keyki" deletions="0" id="c9adf248396baedb1bdd1818a2736c680a3600ca" merge="no"/></root>