<root issues-status="done" commits-status="done"><participant login="kshlm" cnt="6"><period date="201524"><pullrequests>1</pullrequests><comments>1</comments><commits>4</commits><additions>8</additions><deletions>6</deletions></period></participant><participant login="justinclift" cnt="55"><period date="201524"><comments>1</comments><commits>13</commits><additions>138</additions><deletions>50</deletions><mergers>1</mergers></period><period date="201523"><comments>2</comments><commits>7</commits><additions>118</additions><deletions>54</deletions></period><period date="201525"><commits>12</commits><additions>367</additions><deletions>180</deletions></period><period date="201521"><mergers>1</mergers></period><period date="201519"><commits>1</commits><additions>4</additions><deletions>1</deletions></period><period date="201518"><commits>1</commits><additions>1</additions><deletions>0</deletions></period><period date="201516"><commits>16</commits><additions>507</additions><deletions>53</deletions></period></participant><participant login="pcuzner" cnt="3"><period date="201521"><pullrequests>2</pullrequests><commits>1</commits><additions>1</additions><deletions>0</deletions></period></participant></root>